{
    "advisor": "1501001",
    "request": "false",
    "readNotification": [],
    "password": "Nisa123._",
    "transcript": {
        "failedcourses": [],
        "completedcourses": [],
        "termPassed": [],
        "term": 1,
        "gradesFailed": [],
        "gradesPassed": []
    },
    "unreadNotification": [],
    "name": "Nisa",
    "registration": {
        "selectedcourses": [],
        "approvedcourses": []
    },
    "id": "150122025",
    "type": "student",
    "lastname": "Yıldız"
}